Upload/KnoemaUpload.py
Upload/__init__.py
KnoemaUpload-0.4.3.dist-info/LICENSE
KnoemaUpload-0.4.3.dist-info/METADATA
KnoemaUpload-0.4.3.dist-info/WHEEL
KnoemaUpload-0.4.3.dist-info/top_level.txt
KnoemaUpload-0.4.3.dist-info/RECORD
