Metadata-Version: 2.1
Name: KnoemaUpload
Version: 0.4.3
Summary: Used for only internal purpose of the knoema employees to upload files to portal via API.
Home-page: https://github.com/pypa/sampleproject
Author: Vasanth
Author-email: vbalakrishna@knoema.com
Project-URL: Bug Tracker, https://github.com/pypa/sampleproject/issues
Classifier: Programming Language :: Python :: 3
Classifier: License :: OSI Approved :: MIT License
Classifier: Operating System :: OS Independent
Requires-Python: >=3.6
License-File: LICENSE
